json_env/__init__.py
json_env/keys.py
json_env/loader.py
json_env/picker.py
json_env/setter.py
json_env/types.py
json_env_sln-1.2.1.dist-info/LICENSE
json_env_sln-1.2.1.dist-info/METADATA
json_env_sln-1.2.1.dist-info/WHEEL
json_env_sln-1.2.1.dist-info/top_level.txt
json_env_sln-1.2.1.dist-info/RECORD
