Metadata-Version: 2.1
Name: json_env_sln
Version: 1.2.1
Summary: This is a simple environment variable solution for .json file, which is based on 'os' and 'json' lib
Home-page: https://github.com/Asashishi/json_env
Author: Asashishi_Nyan!
Author-email: 1072903224@qq.com
Classifier: Programming Language :: Python :: 3
Classifier: License :: OSI Approved :: MIT License
Classifier: Operating System :: OS Independent
Requires-Python: >=3.7
License-File: LICENSE
